gilman_rgi_to_csv/__init__.py
gilman_rgi_to_csv/main.py
gilman_rgi_to_csv-1.0.dist-info/METADATA
gilman_rgi_to_csv-1.0.dist-info/WHEEL
gilman_rgi_to_csv-1.0.dist-info/entry_points.txt
gilman_rgi_to_csv-1.0.dist-info/top_level.txt
gilman_rgi_to_csv-1.0.dist-info/RECORD
